redturtle.rsync-1.0.7-py3.11-nspkg.pth
redturtle/rsync/__init__.py
redturtle/rsync/configure.zcml
redturtle/rsync/interfaces.py
redturtle/rsync/permissions.zcml
redturtle/rsync/setuphandlers.py
redturtle/rsync/testing.py
redturtle/rsync/adapters/__init__.py
redturtle/rsync/adapters/adapter.py
redturtle/rsync/adapters/configure.zcml
redturtle/rsync/browser/__init__.py
redturtle/rsync/browser/configure.zcml
redturtle/rsync/locales/README.rst
redturtle/rsync/locales/__init__.py
redturtle/rsync/locales/redturtle.rsync.pot
redturtle/rsync/locales/update.py
redturtle/rsync/locales/update.sh
redturtle/rsync/locales/en/LC_MESSAGES/redturtle.rsync.po
redturtle/rsync/locales/it/LC_MESSAGES/redturtle.rsync.po
redturtle/rsync/profiles/default/browserlayer.xml
redturtle/rsync/profiles/default/catalog.xml
redturtle/rsync/profiles/default/metadata.xml
redturtle/rsync/profiles/default/rolemap.xml
redturtle/rsync/profiles/default/registry/main.xml
redturtle/rsync/profiles/uninstall/browserlayer.xml
redturtle/rsync/scripts/__init__.py
redturtle/rsync/scripts/rsync.py
redturtle/rsync/tests/__init__.py
redturtle/rsync/tests/test_robot.py
redturtle/rsync/tests/test_setup.py
redturtle/rsync/tests/robot/test_example.robot
redturtle_rsync-1.0.7.dist-info/licenses/LICENSE.GPL
redturtle_rsync-1.0.7.dist-info/licenses/LICENSE.rst
redturtle_rsync-1.0.7.dist-info/METADATA
redturtle_rsync-1.0.7.dist-info/WHEEL
redturtle_rsync-1.0.7.dist-info/entry_points.txt
redturtle_rsync-1.0.7.dist-info/namespace_packages.txt
redturtle_rsync-1.0.7.dist-info/top_level.txt
redturtle_rsync-1.0.7.dist-info/RECORD
